{
    "MockHome": [
        {
        "title": "Montaña",
        "subtitle": "Lorem ipsum dolor sit amet, consectetur adipiscing elit. Sed do eiusmod tempor incididunt ut labore et dolore magna aliqua.",
        "image": "https://via.placeholder.com/1600x900"
        },
        {
        "title": "Nuestros servicios",
        "subtitle": "Lorem ipsum dolor sit amet, consectetur adipiscing elit. Sed do eiusmod tempor incididunt ut labore et dolore magna aliqua.",
        "image": "https://via.placeholder.com/1600x900"
        },
        {
        "title": "Habitaciones",
        "subtitle": "Lorem ipsum dolor sit amet, consectetur adipiscing elit. Sed do eiusmod tempor incididunt ut labore et dolore magna aliqua.",
        "image": "https://via.placeholder.com/1600x900"
        },
        {
        "title": "Contacto",
        "subtitle": "Lorem ipsum dolor sit amet, consectetur adipiscing elit. Sed do eiusmod tempor incididunt ut labore et dolore magna aliqua.",
        "image": "https://via.placeholder.com/1600x900"
        }
    ],

    "MockServices": [
        {
        "title": "Spa",
        "subtitle": "Lorem ipsum dolor sit amet, consectetur adipiscing elit. Sed do eiusmod tempor incididunt ut labore et dolore magna aliqua.",
        "image": "https://via.placeholder.com/1600x900"
        },
        {
        "title": "Paseos",
        "subtitle": "Lorem ipsum dolor sit amet, consectetur adipiscing elit. Sed do eiusmod tempor incididunt ut labore et dolore magna aliqua.",
        "image": "https://via.placeholder.com/1600x900"
        },
        {
        "title": "Excursiones",
        "subtitle": "Lorem ipsum dolor sit amet, consectetur adipiscing elit. Sed do eiusmod tempor incididunt ut labore et dolore magna aliqua.",
        "image": "https://via.placeholder.com/1600x900"
        },
        {
        "title": "Piscina",
        "subtitle": "Lorem ipsum dolor sit amet, consectetur adipiscing elit. Sed do eiusmod tempor incididunt ut labore et dolore magna aliqua.",
        "image": "https://via.placeholder.com/1600x900"
        }
    ]
}

